fxtracker/__init__.py
fxtracker/fxtracker.py
fxtracker-1.0.3.dist-info/METADATA
fxtracker-1.0.3.dist-info/WHEEL
fxtracker-1.0.3.dist-info/LICENSE
fxtracker-1.0.3.dist-info/RECORD
