Metadata-Version: 2.1
Name: fxtracker
Version: 1.0.3
Summary: A package that plots current and historical price graphs for currency pairs as well as converts currency.
Home-page: https://github.com/UBC-MDS/fxtracker
License: MIT
Author: Sarah Abdelazim, Markus Nam, Crystal Geng, Lennon Au-Yeung
Requires-Python: >=3.9,<4.0
Classifier: License :: OSI Approved :: MIT License
Classifier: Programming Language :: Python :: 3
Classifier: Programming Language :: Python :: 3.9
Classifier: Programming Language :: Python :: 3.10
Classifier: Programming Language :: Python :: 3.11
Requires-Dist: altair (>=4.2.0,<5.0.0)
Requires-Dist: altair-viewer (>=0.4.0,<0.5.0)
Requires-Dist: ipykernel (>=6.20.2,<7.0.0)
Requires-Dist: numpy (>=1.24.1,<2.0.0)
Requires-Dist: pandas (>=1.5.2,<2.0.0)
Requires-Dist: plotly (>=5.12.0,<6.0.0)
Requires-Dist: python-semantic-release (>=7.33.0,<8.0.0)
Requires-Dist: yfinance (>=0.2.3,<0.3.0)
Project-URL: Documentation, https://fxtracker.readthedocs.io
Project-URL: Repository, https://github.com/UBC-MDS/fxtracker
